mmpg_rout/__init__.py
mmpg_rout/route.py
mmpg_rout-0.2.0.dist-info/METADATA
mmpg_rout-0.2.0.dist-info/WHEEL
mmpg_rout-0.2.0.dist-info/entry_points.txt
mmpg_rout-0.2.0.dist-info/top_level.txt
mmpg_rout-0.2.0.dist-info/RECORD
