Metadata-Version: 2.1
Name: mmpg-rout
Version: 0.2.0
Author: Valfrido Novais
Project-URL: Homepage, https://github.com/ValfridoNovais/mmpg-rout
Project-URL: Repository, https://github.com/ValfridoNovais/mmpg-rout
Project-URL: Issues, https://github.com/ValfridoNovais/mmpg-rout/issues
Keywords: route,windows,gateway,networking,impala,bisp,pmmg
Classifier: Programming Language :: Python :: 3
Classifier: Operating System :: Microsoft :: Windows
Classifier: Topic :: System :: Networking
Classifier: License :: OSI Approved :: MIT License
Requires-Python: >=3.8
